[
  {
    "tag": "EVENT",
    "name": "MIA TOWN - RECAP HIGHTLIGHT GAME EVENT",
    "url": "https://youtu.be/ikSyZPlN_d0"
  },
  {
    "tag": "EVENT",
    "name": "CARAVAN",
    "url": "https://youtu.be/OT_YnBgvr7M"
  },
  {
    "tag": "EVENT",
    "name": "SAN GOFT VUNG TAU",
    "url": "https://youtu.be/sz8FxzZHZp8"
  },
  {
    "tag": "EVENT",
    "name": "REDBULL",
    "url": "https://youtu.be/WMSxSdUJI7o"
  },
  {
    "tag": "EVENT",
    "name": "TRUONG DAI HOC CONG NGHE",
    "url": "https://youtu.be/vgzELkbqv1c"
  },
  {
    "tag": "EVENT",
    "name": "WORKSHOP DO NOI THAT",
    "url": "https://youtu.be/HglCm5loN60"
  },
  {
    "tag": "EVENT",
    "name": "TAN GIA & THOI NOI",
    "url": "https://youtu.be/P13zAf28WBA"
  },
  {
    "tag": "EVENT",
    "name": "STAR GAMING - RECAP HIGHIGHT GAME EVENT",
    "url": "https://youtu.be/EV7oDzUv_EQ"
  },
  {
    "tag": "EVENT",
    "name": "RECAP TEAMBUILDING",
    "url": ""
  },
  {
    "tag": "EVENT",
    "name": "RECAP SỰ KIỆN \"ẨN\"",
    "url": ""
  },
  {
    "tag": "PODCAST",
    "name": "PHONG LINH OFFICIAL",
    "url": ""
  },
  {
    "tag": "CLIP",
    "name": "O DOI TA NUNG",
    "url": "https://youtu.be/VMUoYvZALoE"
  },
  {
    "tag": "TVC",
    "name": "DU LICH GIA DINH",
    "url": "https://youtu.be/V5wk2bpnsSk"
  },
  {
    "tag": "TVC",
    "name": "SPA BAR - NGUYEN VAN HUONG (1)",
    "url": "https://youtu.be/mHD3J-irGzs"
  },
  {
    "tag": "TVC",
    "name": "SPA BAR - NGUYEN VAN HUONG (2)",
    "url": "https://youtu.be/2MOQ_4zXvBU"
  },
  {
    "tag": "MV",
    "name": "GREE - 'HẠ TAN' (Prod. by SARTORY) [OFFICIAL MV]",
    "url": "https://youtu.be/aD1rfIurMts"
  },
  {
    "tag": "MV",
    "name": "HONESTLY - RDEE ft. SONIE | OFFICIAL MV",
    "url": "https://youtu.be/dk7E8BUhuq4"
  },
  {
    "tag": "VIRAL CLIP",
    "name": "KET NOI YEU THUONG - CHIA SE HAT LANH",
    "url": "https://youtu.be/qmjAeAyY9pw"
  },
  {
    "tag": "VIRAL CLIP",
    "name": "DOVE - MỪNG NGÀY CỦA MẸ",
    "url": ""
  },
  {
    "tag": "VIRAL CLIP",
    "name": "Phóng sự: Cuộc sống của Sinh viên khi phải sống xa nhà",
    "url": ""
  }
]
